moonstreamtypes/__init__.py
moonstreamtypes/blockchain.py
moonstreamtypes/networks.py
moonstreamtypes/subscriptions.py
moonstreamtypes/version.py
moonstream_types-0.0.11.dist-info/METADATA
moonstream_types-0.0.11.dist-info/WHEEL
moonstream_types-0.0.11.dist-info/top_level.txt
moonstream_types-0.0.11.dist-info/RECORD
